media_uploader_widget/__init__.py
media_uploader_widget/admin.py
media_uploader_widget/widgets.py
media_uploader_widget/locale/es/LC_MESSAGES/django.mo
media_uploader_widget/locale/es/LC_MESSAGES/django.po
media_uploader_widget/locale/pt_BR/LC_MESSAGES/django.mo
media_uploader_widget/locale/pt_BR/LC_MESSAGES/django.po
media_uploader_widget/locale/ru/LC_MESSAGES/django.mo
media_uploader_widget/locale/ru/LC_MESSAGES/django.po
media_uploader_widget/postgres/__init__.py
media_uploader_widget/postgres/fields.py
media_uploader_widget/postgres/forms.py
media_uploader_widget/postgres/widget.py
media_uploader_widget/static/media_uploader_widget/css/media-uploader-inline.css
media_uploader_widget/static/media_uploader_widget/css/media-uploader-widget.css
media_uploader_widget/static/media_uploader_widget/js/media-uploader-inline.js
media_uploader_widget/static/media_uploader_widget/js/media-uploader-modal.js
media_uploader_widget/static/media_uploader_widget/js/media-uploader-widget.js
media_uploader_widget/static/media_uploader_widget/js/vendor/sortable.min.js
media_uploader_widget/templates/media_uploader_widget/admin/inline_media_uploader.html
media_uploader_widget/templates/media_uploader_widget/admin/inline_media_uploader_preview.html
media_uploader_widget/templates/media_uploader_widget/admin/inline_media_uploader_preview_widget.html
media_uploader_widget/templates/media_uploader_widget/admin/ordered_inline_media_uploader.html
media_uploader_widget/templates/media_uploader_widget/parts/preview.html
media_uploader_widget/templates/media_uploader_widget/postgres/media_array.html
media_uploader_widget/templates/media_uploader_widget/postgres/media_array_preview.html
media_uploader_widget/templates/media_uploader_widget/widget/media_uploader_widget.html
media_uploader_widget/templates/media_uploader_widget/widget/media_uploader_widget_preview.html
django_media_uploader_widget-1.0.2.dist-info/LICENSE
django_media_uploader_widget-1.0.2.dist-info/METADATA
django_media_uploader_widget-1.0.2.dist-info/WHEEL
django_media_uploader_widget-1.0.2.dist-info/top_level.txt
django_media_uploader_widget-1.0.2.dist-info/RECORD
